pyscoutfm/__init__.py
pyscoutfm/application.py
pyscoutfm/data.py
pyscoutfm/formatter.py
pyscoutfm/generator.py
pyscoutfm/importer.py
pyscoutfm/config/config.json
pyscoutfm/config/weightings.json
pyscoutfm/extras/PyScoutFM - Player Search.fmf
pyscoutfm/extras/PyScoutFM - Squad.fmf
pyscoutfm-1.1.1.dist-info/LICENSE
pyscoutfm-1.1.1.dist-info/METADATA
pyscoutfm-1.1.1.dist-info/WHEEL
pyscoutfm-1.1.1.dist-info/entry_points.txt
pyscoutfm-1.1.1.dist-info/top_level.txt
pyscoutfm-1.1.1.dist-info/RECORD
