Metadata-Version: 2.1
Name: pyscoutfm
Version: 1.1.1
Summary: Use the power of Python to traverse the cosmos and scout for players within the Football Manager game
Home-page: https://github.com/olimorris/pyscoutfm
Author: Oli Morris
Author-email: olimorris@users.noreply.github.com
License: MIT
Classifier: Programming Language :: Python :: 3
Requires-Python: >=3.10
License-File: LICENSE
Requires-Dist: lxml >=4.9.3
Requires-Dist: pandas >=2.0.0
Requires-Dist: rich >=13.6.0
Requires-Dist: typer >=0.9.0
Provides-Extra: dev
Requires-Dist: pytest >=7.4.3 ; extra == 'dev'
